Metadata-Version: 2.1
Name: odoo14-addon-web_archive_date
Version: 14.0.1.0.2.dev5
Summary: Reflects the Latest Archived Date and Latest Archived by on the record metadata.
Home-page: https://github.com/OCA/server-ux
Author: ForgeFlow, Odoo Community Association (OCA)
Author-email: support@odoo-community.org
License: AGPL-3
Classifier: Programming Language :: Python
Classifier: Framework :: Odoo
Classifier: Framework :: Odoo :: 14.0
Classifier: License :: OSI Approved :: GNU Affero General Public License v3
Requires-Python: >=3.6
Requires-Dist: odoo14-addon-base-archive-date
Requires-Dist: odoo<14.1dev,>=14.0a
